benchkit/__init__.py
benchkit/benchmark.py
benchkit/campaign.py
benchkit/lwchart.py
benchkit/adb/__init__.py
benchkit/adb/fastboot.py
benchkit/adb/flash.py
benchkit/adb/netiface.py
benchkit/adb/usb.py
benchkit/charts/__init__.py
benchkit/charts/analyses.py
benchkit/charts/config.py
benchkit/charts/dataframes.py
benchkit/charts/interactivecharts.py
benchkit/charts/printedcharts.py
benchkit/commandattachments/__init__.py
benchkit/commandattachments/tracecmd.py
benchkit/commandwrappers/__init__.py
benchkit/commandwrappers/env.py
benchkit/commandwrappers/ltrace.py
benchkit/commandwrappers/numactl.py
benchkit/commandwrappers/perf.py
benchkit/commandwrappers/strace.py
benchkit/commandwrappers/taskset.py
benchkit/commandwrappers/valgrind.py
benchkit/communication/__init__.py
benchkit/communication/docker.py
benchkit/communication/utils.py
benchkit/dependencies/__init__.py
benchkit/dependencies/dependency.py
benchkit/dependencies/executables.py
benchkit/dependencies/library.py
benchkit/dependencies/packagemanagers.py
benchkit/dependencies/packages.py
benchkit/helpers/__init__.py
benchkit/helpers/sql.py
benchkit/helpers/linux/__init__.py
benchkit/helpers/linux/build.py
benchkit/helpers/linux/distrib.py
benchkit/helpers/linux/grubentries.py
benchkit/helpers/linux/kernel.py
benchkit/helpers/linux/notes-openeuler.md
benchkit/helpers/linux/numabalancing.py
benchkit/helpers/linux/ps.py
benchkit/helpers/linux/sysctl.py
benchkit/helpers/linux/ulimit.py
benchkit/helpers/linux/patches/hack_acpi_arm_cpufreq_kunpeng_bug.patch
benchkit/helpers/linux/predictable/__init__.py
benchkit/helpers/linux/predictable/cpupower.py
benchkit/helpers/linux/predictable/predlinux.py
benchkit/helpers/linux/predictable/systemctl.py
benchkit/platforms/__init__.py
benchkit/platforms/custom.py
benchkit/platforms/evenorder.py
benchkit/platforms/generic.py
benchkit/platforms/register.py
benchkit/platforms/registerfile.py
benchkit/platforms/servers.py
benchkit/platforms/utils.py
pybenchkit-0.0.1.dist-info/METADATA
pybenchkit-0.0.1.dist-info/WHEEL
pybenchkit-0.0.1.dist-info/licenses/LICENSE
pybenchkit-0.0.1.dist-info/RECORD
