Metadata-Version: 2.3
Name: pybenchkit
Version: 0.0.1
Summary: A push-button end-to-end performance evaluation pipeline for automatically exploring the parameter space.
Project-URL: Homepage, https://github.com/open-s4c/benchkit
Project-URL: Issues, https://github.com/open-s4c/benchkit/issues
Author-email: Antonio Paolillo <antonio@paolillo.be>
License-File: LICENSE
Classifier: License :: OSI Approved :: MIT License
Classifier: Operating System :: OS Independent
Classifier: Programming Language :: Python :: 3
Requires-Python: >=3.10
